karmapi/__init__.py
karmapi/addnulls.py
karmapi/base.py
karmapi/bats.py
karmapi/battery.py
karmapi/beanstalk.py
karmapi/carpet.py
karmapi/checksum.py
karmapi/chess.py
karmapi/cpr.py
karmapi/currie.py
karmapi/diceware.py
karmapi/dicewords.py
karmapi/envy.py
karmapi/epigume.py
karmapi/eric.py
karmapi/filly.py
karmapi/finder.py
karmapi/flash.py
karmapi/gilliam.py
karmapi/grb.py
karmapi/heart.py
karmapi/hipflask.py
karmapi/hju.py
karmapi/hush.py
karmapi/joy.py
karmapi/joy2.py
karmapi/kiss.py
karmapi/klein.py
karmapi/kpi.py
karmapi/locations.py
karmapi/magnet.py
karmapi/maps.py
karmapi/match.py
karmapi/mayqueen.py
karmapi/mclock2.py
karmapi/milk.py
karmapi/mj.py
karmapi/model.py
karmapi/moon.py
karmapi/music.py
karmapi/ncdf.py
karmapi/nhc.py
karmapi/noddy.py
karmapi/nzquake.py
karmapi/oo2ueh.py
karmapi/orongo.py
karmapi/pear.py
karmapi/pig.py
karmapi/pigfarm.py
karmapi/pigjoy.py
karmapi/piglet.py
karmapi/pixin.py
karmapi/prime.py
karmapi/rainbow.py
karmapi/rdict.py
karmapi/read_fix.py
karmapi/roikpi.py
karmapi/sense.py
karmapi/show.py
karmapi/shrink.py
karmapi/some.py
karmapi/sonogram.py
karmapi/sunny.py
karmapi/talk.py
karmapi/tankrain.py
karmapi/tgp.py
karmapi/times.py
karmapi/toy.py
karmapi/tpot.py
karmapi/udmace.py
karmapi/usgs.py
karmapi/veyes.py
karmapi/weather.py
karmapi/weird.py
karmapi/widgets.py
karmapi/words.py
karmapi/yosser.py
karmapi/zen.py
karmapi/apis/__init__.py
karmapi/apis/base.py
karmapi/apis/euro.py
karmapi/apis/stats.py
karmapi/backends/__init__.py
karmapi/backends/core.py
karmapi/backends/hatpig.py
karmapi/backends/qtpig.py
karmapi/backends/tkpig.py
karmapi/backends/webpig.py
karmapi/meta/__init__.py
karmapi/meta/weather.py
karmapi/models/__init__.py
karmapi/models/lat_lon_grid.py
karmapi/models/lists.py
karmapi/tools/__init__.py
karmapi/tools/build.py
karmapi/tools/image.py
karmapi/wc/__init__.py
karmapi/wc/events.py
karmapi/wc/game.py
karmapi-1.3141592.dist-info/METADATA
karmapi-1.3141592.dist-info/RECORD
karmapi-1.3141592.dist-info/WHEEL
karmapi-1.3141592.dist-info/dependency_links.txt
karmapi-1.3141592.dist-info/entry_points.txt
karmapi-1.3141592.dist-info/top_level.txt
