Metadata-Version: 2.1
Name: karmapi
Version: 1.3141592
Summary: Data with karma and pi
Home-page: https://github.com/swfiua/karmapi
Author: Johnny Gill
Author-email: swfiua@gmail.com
License: GPL v 3
Keywords: data pi karma
Platform: UNKNOWN
Classifier: Development Status :: 3 - Alpha
Classifier: Intended Audience :: Science/Research
Classifier: Programming Language :: Python :: 3.6
Requires-Dist: astropy
Requires-Dist: matplotlib
Requires-Dist: pandas
Requires-Dist: curio
Requires-Dist: Pillow
Requires-Dist: pytest
Requires-Dist: hypothesis
Requires-Dist: requests
